{"name":"Xfce4-taskmanager","tagline":"Mirror of git://git.xfce.org/apps/xfce4-taskmanager","body":"*********************************************\r\n\r\nxfce4-taskmanager -- Easy to use task manager\r\n\r\n*********************************************\r\n\r\n** Retrieving **\r\n\r\nThe latest version of xfce4-taskmanager can always be obtained from\r\nhttp://goodies.xfce.org/releases/xfce4-taskmanager/. Please check to \r\nsee if there is a newer version available before reporting bugs.\r\n\r\n** Requirements **\r\n\r\nGTK+ 2.12\r\nCairo 1.5\r\nLibwnck 2.0 (optional)\r\n\r\n** Building **\r\n\r\n./configure\r\nmake\r\nmake install (as root if needed)\r\n\r\n** Usage **\r\n\r\nThe GUI can be started by running 'xfce4-taskmanager'.\r\n","google":"","note":"Don't delete this file! It's used internally to help with page regeneration."}